scaminsight2/__init__.py
scaminsight2/main.py
scaminsight2/scaminsight.py
scaminsight2-0.0.18.data/scripts/main.py
scaminsight2-0.0.18.dist-info/METADATA
scaminsight2-0.0.18.dist-info/WHEEL
scaminsight2-0.0.18.dist-info/entry_points.txt
scaminsight2-0.0.18.dist-info/top_level.txt
scaminsight2-0.0.18.dist-info/RECORD
