Metadata-Version: 2.1
Name: scaminsight2
Version: 0.0.18
Summary: 하와왕
Home-page: https://github.com/test
Author: tester
Author-email: tester@gmail.com
License: MIT
Classifier: Programming Language :: Python :: 3.6
Classifier: Programming Language :: Python :: 3.7
Classifier: Programming Language :: Python :: 3.8
Classifier: Programming Language :: Python :: 3.9
Requires-Python: >=3.6
Requires-Dist: python-whois
Requires-Dist: bs4
Requires-Dist: selenium
Requires-Dist: chromedriver-autoinstaller
